{"_ts":[1559352442],"_r":{"breakdown":{"html":{"bytes":[7733],"requests":[1]},"js":{"bytes":[287644],"requests":[9]},"css":{"bytes":[110228],"requests":[2]},"image":{"bytes":[116029],"requests":[6]},"flash":{"bytes":[0],"requests":[0]},"font":{"bytes":[77158],"requests":[1]},"video":{"bytes":[0],"requests":[0]},"other":{"bytes":[179],"requests":[1]}},"date":[1559352442],"domElements":[117],"domInteractive":[1418],"firstPaint":[1296.7199999985],"fullyLoaded":[2473],"id":["190601_G6_22523e5afb86bb8959c058f8c0a7685d"],"loadTime":[2268],"render":[1500],"SpeedIndex":[1514],"TTFB":[583],"videoFrames":[[{"_i":"ms_000000.jpg","_t":0,"_vc":0},{"_i":"ms_001500.jpg","_t":1500,"_vc":95},{"_i":"ms_001700.jpg","_t":1700,"_vc":96},{"_i":"ms_001800.jpg","_t":1800,"_vc":100}]],"visualComplete":[1800],"lighthouse":[54],"pagespeed":[81]}}