{"_ts":[1564619785,1564706811],"_r":{"breakdown":{"html":{"bytes":[34880,34895],"requests":[1,1]},"js":{"bytes":[345431,345431],"requests":[19,19]},"css":{"bytes":[133227,133227],"requests":[5,5]},"image":{"bytes":[26112,26112],"requests":[8,8]},"flash":{"bytes":[0,0],"requests":[0,0]},"font":{"bytes":[197591,197591],"requests":[4,4]},"video":{"bytes":[0,0],"requests":[0,0]},"other":{"bytes":[0,0],"requests":[0,0]}},"date":[1564619785,1564706811],"domElements":[268,268],"domInteractive":[1566,1582],"firstPaint":[1657.5300000004,1680.6949999991],"fullyLoaded":[2646,2650],"id":["190801_QA_126753e9175688e3fe795c24dc870427","190802_MJ_d006ba15d302baac599c78cc5e9fd660"],"loadTime":[2535,2540],"render":[1600,1600],"SpeedIndex":[1621,1621],"TTFB":[575,582],"videoFrames":[[{"_i":"ms_000000.jpg","_t":0,"_vc":0},{"_i":"ms_001600.jpg","_t":1600,"_vc":92},{"_i":"ms_001700.jpg","_t":1700,"_vc":92},{"_i":"ms_001800.jpg","_t":1800,"_vc":99},{"_i":"ms_002000.jpg","_t":2000,"_vc":99},{"_i":"ms_002200.jpg","_t":2200,"_vc":100},{"_i":"ms_002300.jpg","_t":2300,"_vc":99},{"_i":"ms_002400.jpg","_t":2400,"_vc":100}],[{"_i":"ms_000000.jpg","_t":0,"_vc":0},{"_i":"ms_001600.jpg","_t":1600,"_vc":92},{"_i":"ms_001700.jpg","_t":1700,"_vc":92},{"_i":"ms_001800.jpg","_t":1800,"_vc":99},{"_i":"ms_002000.jpg","_t":2000,"_vc":99},{"_i":"ms_002300.jpg","_t":2300,"_vc":100},{"_i":"ms_002400.jpg","_t":2400,"_vc":100}]],"visualComplete":[2200,2300],"lighthouse":[54,54],"pagespeed":[84,84]}}